guardtypes/__init__.py
guardtypes/core.py
guardtypes-1.0.2.dist-info/LICENSE
guardtypes-1.0.2.dist-info/METADATA
guardtypes-1.0.2.dist-info/WHEEL
guardtypes-1.0.2.dist-info/top_level.txt
guardtypes-1.0.2.dist-info/RECORD
